bareduckdb-0.3.142.dist-info/RECORD
bareduckdb-0.3.142.dist-info/WHEEL
bareduckdb-0.3.142.dist-info/top_level.txt
bareduckdb-0.3.142.dist-info/METADATA
bareduckdb-0.3.142.dist-info/licenses/LICENSE
bareduckdb/_version.py
bareduckdb/__init__.py
bareduckdb/_utils.py
bareduckdb/compat/__init__.py
bareduckdb/compat/connection_compat.py
bareduckdb/compat/result_compat.py
bareduckdb/compat/__pycache__/result_compat.cpython-314.pyc
bareduckdb/compat/__pycache__/connection_compat.cpython-314.pyc
bareduckdb/compat/__pycache__/__init__.cpython-314.pyc
bareduckdb/core/__init__.py
bareduckdb/core/connection_base.py
bareduckdb/core/impl/connection.pyx
bareduckdb/core/impl/result.pyx
bareduckdb/core/impl/__init__.py
bareduckdb/core/impl/python_to_value.pyx
bareduckdb/core/impl/result.cpython-314t-darwin.so
bareduckdb/core/impl/python_to_value.pxd
bareduckdb/core/impl/python_to_value.cpp
bareduckdb/core/impl/result.pxd
bareduckdb/core/impl/cpp_helpers.hpp
bareduckdb/core/impl/python_to_value.cpython-314t-darwin.so
bareduckdb/core/impl/result.cpp
bareduckdb/core/impl/connection.pxd
bareduckdb/core/impl/connection.cpp
bareduckdb/core/impl/connection.cpython-314t-darwin.so
bareduckdb/core/impl/arrow_cardinality.hpp
bareduckdb/core/impl/__pycache__/__init__.cpython-314.pyc
bareduckdb/core/__pycache__/__init__.cpython-314.pyc
bareduckdb/core/__pycache__/connection_base.cpython-314.pyc
bareduckdb/dataset/backend.py
bareduckdb/dataset/__init__.py
bareduckdb/dataset/impl/dataset.pyx
bareduckdb/dataset/impl/arrow_scan_dataset.hpp
bareduckdb/dataset/impl/__init__.py
bareduckdb/dataset/impl/dataset.cpython-314t-darwin.so
bareduckdb/dataset/impl/dataset.cpp
bareduckdb/dataset/impl/dataset.pxd
bareduckdb/aio/async_connection.py
bareduckdb/__pycache__/_version.cpython-314.pyc
bareduckdb/__pycache__/_utils.cpython-314.pyc
bareduckdb/__pycache__/__init__.cpython-314.pyc
bareduckdb/_libs/libduckdb.dylib
bareduckdb/functional/__init__.py
bareduckdb/functional/__pycache__/__init__.cpython-314.pyc
