Metadata-Version: 2.4
Name: bareduckdb
Version: 0.3.142
Summary: Minimal Cython-based DuckDB Bindings
Author-email: Paul T <paul@iqmo.com>
License-Expression: MIT
Classifier: Development Status :: 3 - Alpha
Classifier: Intended Audience :: Developers
Classifier: Programming Language :: Python :: 3
Classifier: Programming Language :: Python :: 3.12
Classifier: Programming Language :: Python :: 3.13
Classifier: Programming Language :: Python :: 3.14
Classifier: Programming Language :: Python :: 3 :: Only
Classifier: Programming Language :: Python :: Implementation :: CPython
Classifier: Programming Language :: Cython
Classifier: Programming Language :: Python :: Free Threading
Classifier: Topic :: Database
Classifier: Topic :: Software Development :: Libraries :: Python Modules
Classifier: Typing :: Typed
Classifier: Operating System :: OS Independent
Requires-Python: >=3.12
License-File: LICENSE
Requires-Dist: typing-extensions>=4.15.0
Provides-Extra: arrow
Requires-Dist: pyarrow==22.0; extra == "arrow"
Provides-Extra: test
Requires-Dist: pytest>=8.4.2; extra == "test"
Requires-Dist: pytest-asyncio>=0.24.0; extra == "test"
Requires-Dist: pytest-xdist>=3.8.0; extra == "test"
Requires-Dist: pytest-cov>=6.0.0; extra == "test"
Requires-Dist: pytest-timeout>=2.3.1; extra == "test"
Requires-Dist: pytest-randomly>=4.0.1; extra == "test"
Requires-Dist: pytest-run-parallel>=0.2.0; extra == "test"
Requires-Dist: pytest-forked>=1.6.0; extra == "test"
Requires-Dist: pyarrow>=22.0; extra == "test"
Requires-Dist: pandas; python_version < "3.14" and extra == "test"
Dynamic: license-file
